README.rst
setup.cfg
setup.py
myeventhub/__init__.py
myeventhub/api_models.py
myeventhub/client.py
myeventhub/exceptions.py
myeventhub/options.py
myeventhub/tests.py
python_myeventhub.egg-info/PKG-INFO
python_myeventhub.egg-info/SOURCES.txt
python_myeventhub.egg-info/dependency_links.txt
python_myeventhub.egg-info/requires.txt
python_myeventhub.egg-info/top_level.txt