Metadata-Version: 1.1
Name: python-myeventhub
Version: 0.1.1
Summary: Python API client for MyEventHub.ru
Home-page: https://github.com/DirectlineDev/python-myeventhub
Author: Anton Kuzmichev
Author-email: assargin@gmail.com
License: Apache Software License
Download-URL: https://github.com/DirectlineDev/python-myeventhub/archive/master.zip
Keywords: python,myeventhub,myeventhub.ru,eventhub,myeventhub api
Platform: UNKNOWN
Classifier: Development Status :: 4 - Beta
Classifier: Intended Audience :: Developers
Classifier: License :: OSI Approved :: Apache Software License
Classifier: Operating System :: OS Independent
Classifier: Programming Language :: Python
Classifier: Programming Language :: Python :: 2
Classifier: Programming Language :: Python :: 2.7
Classifier: Programming Language :: Python :: 3
Classifier: Programming Language :: Python :: 3.4
Requires: six
